morphlib/__init__.py
morphlib/lang_code.py
morphlib/main.py
apids_morphlib-0.1.1.dist-info/LICENSE
apids_morphlib-0.1.1.dist-info/METADATA
apids_morphlib-0.1.1.dist-info/WHEEL
apids_morphlib-0.1.1.dist-info/top_level.txt
apids_morphlib-0.1.1.dist-info/RECORD
