Metadata-Version: 2.2
Name: apids_morphlib
Version: 0.1.1
Summary: A library that fetches morphological data from Wiktionary and AI models.
Author-email: Deepak Singh <iamdeepaksingh100@gmail.com>
License: MIT License
Project-URL: Homepage, https://github.com/username/morphlib
Project-URL: Issues, https://github.com/username/morphlib/issues
Keywords: linguistics,morphology,wiktionary,fastapi
Classifier: Programming Language :: Python :: 3
Classifier: License :: OSI Approved :: MIT License
Classifier: Operating System :: OS Independent
License-File: LICENSE
Requires-Dist: fastapi==0.111.1
Requires-Dist: pydantic==2.9.2
Requires-Dist: openai==1.59.7
Requires-Dist: python-dotenv==1.0.1
Requires-Dist: tenacity==9.0.0
Requires-Dist: requests==2.32.3
Requires-Dist: langchain_community==0.3.14
Requires-Dist: playwright==1.49.1
Requires-Dist: tiktoken==0.8.0
Requires-Dist: uvicorn==0.22.0
Provides-Extra: test
Requires-Dist: pytest>=7.0; extra == "test"
